cmake_tidy/__init__.py
cmake_tidy/__main__.py
cmake_tidy/run.py
cmake_tidy/version.py
cmake_tidy/commands/__init__.py
cmake_tidy/commands/command.py
cmake_tidy/commands/format/__init__.py
cmake_tidy/commands/format/format_command.py
cmake_tidy/commands/format/format_configuration.py
cmake_tidy/commands/format/output_writer.py
cmake_tidy/formatting/__init__.py
cmake_tidy/formatting/cmake_format_dispatcher.py
cmake_tidy/formatting/cmake_formatter.py
cmake_tidy/formatting/settings.json
cmake_tidy/formatting/settings_reader.py
cmake_tidy/formatting/utils/__init__.py
cmake_tidy/formatting/utils/format_arguments.py
cmake_tidy/formatting/utils/format_bracket_argument.py
cmake_tidy/formatting/utils/format_command_invocation.py
cmake_tidy/formatting/utils/format_end_command_invocation.py
cmake_tidy/formatting/utils/format_file.py
cmake_tidy/formatting/utils/format_newline.py
cmake_tidy/formatting/utils/format_spaces.py
cmake_tidy/formatting/utils/format_start_command_invocation.py
cmake_tidy/formatting/utils/format_unquoted_argument.py
cmake_tidy/formatting/utils/line_length_calculator.py
cmake_tidy/formatting/utils/single_indent.py
cmake_tidy/formatting/utils/tokens.py
cmake_tidy/formatting/utils/invocation/__init__.py
cmake_tidy/formatting/utils/invocation/command_formatter.py
cmake_tidy/formatting/utils/invocation/command_realign_modifier.py
cmake_tidy/formatting/utils/invocation/command_splitter.py
cmake_tidy/formatting/utils/invocation/condition_formatter.py
cmake_tidy/formatting/utils/invocation/invocation_formatter.py
cmake_tidy/formatting/utils/invocation/invocation_wrapper.py
cmake_tidy/formatting/utils/invocation/line_comments_formatter.py
cmake_tidy/formatting/utils/updaters/__init__.py
cmake_tidy/formatting/utils/updaters/command_invocatin_state_updater.py
cmake_tidy/formatting/utils/updaters/keyword_state_updater.py
cmake_tidy/lexical_data/__init__.py
cmake_tidy/lexical_data/elements.py
cmake_tidy-0.5.0.dist-info/DESCRIPTION.rst
cmake_tidy-0.5.0.dist-info/METADATA
cmake_tidy-0.5.0.dist-info/RECORD
cmake_tidy-0.5.0.dist-info/WHEEL
cmake_tidy-0.5.0.dist-info/entry_points.txt
cmake_tidy-0.5.0.dist-info/metadata.json
cmake_tidy-0.5.0.dist-info/top_level.txt
